<OverlayData>
	<POIs>
		<POI MapID="31" xpos="1094.67" ypos="67.7847" zpos="414.135" type="cmm.cmm_marks.cmm_wood.cmm_greenwood" GUID="250iR5Af0U6SQ4TTZPcjhg=="/>
		<POI MapID="31" xpos="1155.58" ypos="84.3556" zpos="512.314" type="cmm.cmm_marks.cmm_wood.cmm_greenwood" GUID="8Eg0CAEmOEm368nv6ns0jw=="/>
		<POI MapID="31" xpos="942.206" ypos="56.3946" zpos="425.449" type="cmm.cmm_marks.cmm_ore.cmm_normore.cmm_copper" GUID="sKmM8lbRGECNVCCAniGQ1w=="/>
		<POI MapID="31" xpos="876.032" ypos="48.1199" zpos="468.724" type="cmm.cmm_marks.cmm_ore.cmm_normore.cmm_copper" GUID="6t4TWhgVSEGl1rfo9kxtzA=="/>
		<POI MapID="31" xpos="813.771" ypos="40.6503" zpos="498.148" type="cmm.cmm_marks.cmm_ore.cmm_richore.cmm_richiron" GUID="htF0xg6If0mpN8K4aMhC7g=="/>
		<POI MapID="31" xpos="1074.21" ypos="96.8837" zpos="-321.029" type="cmm.cmm_marks.cmm_wood.cmm_softwood" GUID="4JIivNFpU0WLZe7403Lj2Q=="/>
		<POI MapID="31" xpos="1040.73" ypos="125.298" zpos="-265.287" type="cmm.cmm_marks.cmm_ore.cmm_normore.cmm_silver" GUID="dGwQkFKFw0uotc5FOE1nTA=="/>
		<POI MapID="31" xpos="984.049" ypos="103.687" zpos="-264.918" type="cmm.cmm_marks.cmm_ore.cmm_normore.cmm_iron" GUID="J6Cg7VjqYEyV6Ch+3pt/gg=="/>
		<POI MapID="31" xpos="902.443" ypos="84.3375" zpos="-205.527" type="cmm.cmm_marks.cmm_wood.cmm_softwood" GUID="tlXiRjL1dkCqoUXSrOgZ7w=="/>
		<POI MapID="31" xpos="840.993" ypos="87.3669" zpos="-186.531" type="cmm.cmm_marks.cmm_ore.cmm_normore.cmm_iron" GUID="M/jjRl6ONUaz91XhEm61HQ=="/>
		<POI MapID="31" xpos="733.013" ypos="38.0896" zpos="-96.853" type="cmm.cmm_marks.cmm_ore.cmm_richore.cmm_richiron" GUID="KvvYU5CvAUCzDZ6aYIXi7Q=="/>
		<POI MapID="31" xpos="719.452" ypos="37.708" zpos="-122.578" type="cmm.cmm_marks.cmm_ore.cmm_normore.cmm_silver" GUID="VIMCG0g6C0urJxRMR++kHg=="/>
		<POI MapID="31" xpos="592.982" ypos="53.4524" zpos="-125.229" type="cmm.cmm_marks.cmm_ore.cmm_normore.cmm_silver" GUID="8wTwUHhIHE6TwGA+OvsqEw=="/>
		<POI MapID="31" xpos="535.017" ypos="60.8955" zpos="-114.291" type="cmm.cmm_marks.cmm_wood.cmm_softwood" GUID="yLSk6g3gIU+I4j24keegOg=="/>
		<POI MapID="31" xpos="303.703" ypos="32.5055" zpos="35.043" type="cmm.cmm_marks.cmm_ore.cmm_normore.cmm_silver" GUID="Z3Un5Yuysk2usPoaCT27ZA=="/>
		<POI MapID="31" xpos="273.809" ypos="42.5678" zpos="110.727" type="cmm.cmm_marks.cmm_ore.cmm_normore.cmm_iron" GUID="X9akG6URM0ueJkXMsY7Vdg=="/>
		<POI MapID="31" xpos="220.833" ypos="68.8325" zpos="63.8942" type="cmm.cmm_marks.cmm_wood.cmm_softwood" GUID="SR81noMOkEurrjH19XA7ag=="/>
		<POI MapID="31" xpos="341.243" ypos="81.1343" zpos="385.581" type="cmm.cmm_marks.cmm_ore.cmm_normore.cmm_silver" GUID="7JVe6FTA4k6OvlGsp767SQ=="/>
		<POI MapID="31" xpos="473.559" ypos="58.6694" zpos="311.062" type="cmm.cmm_marks.cmm_wood.cmm_softwood" GUID="vQ34oPyedUqZ2KU/uCA8Ng=="/>
		<POI MapID="31" xpos="402.355" ypos="87.0739" zpos="222.035" type="cmm.cmm_marks.cmm_ore.cmm_normore.cmm_iron" GUID="LE3ghCi5Lk+VAfUV41yF3w=="/>
		<POI MapID="31" xpos="679.956" ypos="37.6334" zpos="63.8963" type="cmm.cmm_marks.cmm_wood.cmm_softwood" GUID="iJjjAn7L00OJj9Nu/BxWpg=="/>
		<POI MapID="31" xpos="869.225" ypos="49.2053" zpos="-17.481" type="cmm.cmm_marks.cmm_ore.cmm_normore.cmm_iron" GUID="+tceyv/iLUCTPRfEB9E2Fw=="/>
		<POI MapID="31" xpos="986.901" ypos="113.27" zpos="-466.124" type="cmm.cmm_marks.cmm_ore.cmm_normore.cmm_iron" GUID="KENSmbUmNUasGyOwVoYYcg=="/>
		<POI MapID="31" xpos="811.772" ypos="89.4649" zpos="-307.231" type="cmm.cmm_marks.cmm_ore.cmm_normore.cmm_silver" GUID="mfG0MtTb/0CKzCd5UsYTKA=="/>
		<POI MapID="31" xpos="28.3145" ypos="8.23193" zpos="-460.214" type="cmm.cmm_marks.cmm_ore.cmm_normore.cmm_silver" GUID="y2t4osTuQ0G8jW9SmmEZpA=="/>
		<POI MapID="31" xpos="-125.915" ypos="4.82025" zpos="-257.302" type="cmm.cmm_marks.cmm_ore.cmm_normore.cmm_iron" GUID="/ZKFZ9TWREq7Iij3WQ5sbw=="/>
		<POI MapID="31" xpos="-62.1848" ypos="15.8217" zpos="-269.362" type="cmm.cmm_marks.cmm_ore.cmm_richore.cmm_richsilver" GUID="ht8C/uQ3XU6rUGyG9J+Nxw=="/>
		<POI MapID="31" xpos="-261.959" ypos="24.6479" zpos="-234.779" type="cmm.cmm_marks.cmm_ore.cmm_normore.cmm_iron" GUID="asBXPZnKUk6OZ6VKvRSjjQ=="/>
		<POI MapID="31" xpos="-399.551" ypos="21.5103" zpos="-115.719" type="cmm.cmm_marks.cmm_wood.cmm_softwood" GUID="z196of1BsU2qZHeMapP9Cw=="/>
		<POI MapID="31" xpos="-320.389" ypos="4.28618" zpos="-3.67861" type="cmm.cmm_marks.cmm_ore.cmm_normore.cmm_iron" GUID="R48+oONXLE6rE05b+jAwIg=="/>
		<POI MapID="31" xpos="-270.868" ypos="29.683" zpos="136.166" type="cmm.cmm_marks.cmm_ore.cmm_normore.cmm_iron" GUID="y/rUu02vK0m2c9SdKmkvKg=="/>
		<POI MapID="31" xpos="-293.549" ypos="3.54045" zpos="172.022" type="cmm.cmm_marks.cmm_wood.cmm_softwood" GUID="egpurvWS1UutOJpFH+OW7A=="/>
		<POI MapID="31" xpos="-336.518" ypos="4.3411" zpos="259.715" type="cmm.cmm_marks.cmm_wood.cmm_softwood" GUID="lXN47rlNQECDL2Cgyeiz1A=="/>
		<POI MapID="31" xpos="-237.489" ypos="33.7145" zpos="346.018" type="cmm.cmm_marks.cmm_ore.cmm_richore.cmm_richsilver" GUID="o5KqeDoNG0yPUi8KUro5uA=="/>
		<POI MapID="31" xpos="-213.318" ypos="11.2174" zpos="391.235" type="cmm.cmm_marks.cmm_wood.cmm_softwood" GUID="0wjiLredcUyRWz0qo5vFdQ=="/>
		<POI MapID="31" xpos="-255.293" ypos="5.96288" zpos="401.09" type="cmm.cmm_marks.cmm_wood.cmm_softwood" GUID="nOf26nHwNkyaArUglcf+zA=="/>
		<POI MapID="31" xpos="-49.7296" ypos="45.0285" zpos="475.226" type="cmm.cmm_marks.cmm_wood.cmm_softwood" GUID="wT7Sx222L0SiRtjSKmFiQw=="/>
		<POI MapID="31" xpos="-68.4483" ypos="27.1259" zpos="478.978" type="cmm.cmm_marks.cmm_ore.cmm_normore.cmm_silver" GUID="tflIZZIY7UOKtKy+qFChCg=="/>
		<POI MapID="31" xpos="51.0214" ypos="46.3101" zpos="529.142" type="cmm.cmm_marks.cmm_ore.cmm_normore.cmm_silver" GUID="KLYq+Z+oKEeSznny2/juQQ=="/>
		<POI MapID="31" xpos="117.476" ypos="66.3926" zpos="440.371" type="cmm.cmm_marks.cmm_ore.cmm_normore.cmm_iron" GUID="iUSTaftAs0uqh2+xDHZaJg=="/>
		<POI MapID="31" xpos="102.772" ypos="93.4673" zpos="246.168" type="cmm.cmm_marks.cmm_wood.cmm_softwood" GUID="rkphCBa2fkSMO+IWhN4yOg=="/>
		<POI MapID="31" xpos="22.601" ypos="77.0484" zpos="-131.045" type="cmm.cmm_marks.cmm_wood.cmm_softwood" GUID="mIP7/f6IuUarVjrf4xGQcw=="/>
		<POI MapID="31" xpos="110.221" ypos="45.8347" zpos="-257.504" type="cmm.cmm_marks.cmm_ore.cmm_normore.cmm_silver" GUID="/2h/3LujXUmgo3KyAx1b7Q=="/>
		<POI MapID="31" xpos="186.718" ypos="10.986" zpos="-299.556" type="cmm.cmm_marks.cmm_wood.cmm_softwood" GUID="OQan5XY03kCJD3o3QdqBGQ=="/>
		<POI MapID="31" xpos="-411.981" ypos="20.7609" zpos="-237.529" type="cmm.cmm_marks.cmm_ore.cmm_normore.cmm_silver" GUID="Fa0RXt+Zs0Wta8kDSNHJ6Q=="/>
		<POI MapID="31" xpos="-395.853" ypos="27.9096" zpos="-435.349" type="cmm.cmm_marks.cmm_wood.cmm_softwood" GUID="fzb83cz340aTQdnHTyHuSQ=="/>
		<POI MapID="31" xpos="-819.142" ypos="62.8837" zpos="-539.514" type="cmm.cmm_marks.cmm_ore.cmm_normore.cmm_silver" GUID="OZOEOeVgZ0+KFU/+upeWmg=="/>
		<POI MapID="31" xpos="-850.341" ypos="55.8218" zpos="-562.892" type="cmm.cmm_marks.cmm_ore.cmm_normore.cmm_iron" GUID="Opo4Rfh8WUaaOwAfjWrrJw=="/>
		<POI MapID="31" xpos="-860.243" ypos="57.2719" zpos="-555.57" type="cmm.cmm_marks.cmm_ore.cmm_normore.cmm_silver" GUID="FVbSx5HO50SuZGaJCK9Jag=="/>
		<POI MapID="31" xpos="-1093.71" ypos="52.9858" zpos="-159.327" type="cmm.cmm_marks.cmm_wood.cmm_softwood" GUID="FvwcIczAV0SqPhwiXJxDUA=="/>
		<POI MapID="31" xpos="-1176.94" ypos="51.5446" zpos="-192.576" type="cmm.cmm_marks.cmm_ore.cmm_normore.cmm_iron" GUID="kE2EmZIcNky0Ahoaaao1Jw=="/>
		<POI MapID="31" xpos="-1153.71" ypos="93.4931" zpos="-35.2359" type="cmm.cmm_marks.cmm_ore.cmm_normore.cmm_silver" GUID="/3rynia56EyhkdmLC+MeTA=="/>
		<POI MapID="31" xpos="-1055.98" ypos="83.7733" zpos="-22.409" type="cmm.cmm_marks.cmm_ore.cmm_normore.cmm_silver" GUID="LFLMEj7lLkyp95cBtcybnQ=="/>
		<POI MapID="31" xpos="-949.997" ypos="51.0114" zpos="-25.0601" type="cmm.cmm_marks.cmm_wood.cmm_softwood" GUID="CEI35WCN6kKhUUPyjwDQ+w=="/>
		<POI MapID="31" xpos="-998.588" ypos="91.8771" zpos="242.002" type="cmm.cmm_marks.cmm_wood.cmm_softwood" GUID="YgwkXaX3N0iO1uAn4mzfew=="/>
		<POI MapID="31" xpos="-840.746" ypos="72.1891" zpos="333.611" type="cmm.cmm_marks.cmm_ore.cmm_normore.cmm_iron" GUID="tygvDR1tHUyY5Onq0kbxyA=="/>
		<POI MapID="31" xpos="-776.095" ypos="53.5038" zpos="214.086" type="cmm.cmm_marks.cmm_ore.cmm_normore.cmm_iron" GUID="wfycsosc2UebIpC8duFTyg=="/>
		<POI MapID="31" xpos="-853.856" ypos="52.4431" zpos="144.203" type="cmm.cmm_marks.cmm_ore.cmm_normore.cmm_iron" GUID="pnJmbwSYCEip7jOGfuNUOw=="/>
		<POI MapID="31" xpos="-798.939" ypos="56.4007" zpos="37.2136" type="cmm.cmm_marks.cmm_ore.cmm_normore.cmm_iron" GUID="W70JO6+QPUa4qTyH7prn2g=="/>
		<POI MapID="31" xpos="-599.986" ypos="43.4721" zpos="-142.631" type="cmm.cmm_marks.cmm_ore.cmm_normore.cmm_iron" GUID="MiA+Jf+JUk2FKIVEyiYpFw=="/>
		<POI MapID="31" xpos="-605.049" ypos="50.7847" zpos="-83.0061" type="cmm.cmm_marks.cmm_wood.cmm_softwood" GUID="EHKPFIewXkKrsmN7++kMgA=="/>
		<POI MapID="31" xpos="-570.431" ypos="19.7133" zpos="191.94" type="cmm.cmm_marks.cmm_ore.cmm_normore.cmm_silver" GUID="k6sBJQ62AEipsiLsoA7gRQ=="/>
		<POI MapID="31" xpos="-520.431" ypos="9.08153" zpos="259.844" type="cmm.cmm_marks.cmm_ore.cmm_normore.cmm_iron" GUID="mqHype53kkOiaGpVuQE23Q=="/>
		<POI MapID="31" xpos="1112.67" ypos="71.1111" zpos="466.281" type="cmm.cmm_marks.cmm_wood.cmm_greenwood" GUID="3oQnrVUvmkOcJaA4zzmiFw=="/>
		<POI MapID="31" xpos="1086.33" ypos="75.8182" zpos="459.5" type="cmm.cmm_marks.cmm_wood.cmm_greenwood" GUID="ifONJZmlZUaJ4vkYzlQAJA=="/>
		<POI MapID="31" xpos="968.41" ypos="46.2537" zpos="503.681" type="cmm.cmm_marks.cmm_forage.cmm_fungus.cmm_mushroom" GUID="soz7FPZmsUGAmEOoYLBsRQ=="/>
		<POI MapID="31" xpos="897.56" ypos="50.054" zpos="512.156" type="cmm.cmm_marks.cmm_forage.cmm_fungus.cmm_mushroom" GUID="Ap4B864B20q1UtEj42zB3w=="/>
		<POI MapID="31" xpos="889.97" ypos="49.186" zpos="524.146" type="cmm.cmm_marks.cmm_ore.cmm_normore.cmm_copper" GUID="5mc1aENl8UiJ8sc5d3jEgA=="/>
		<POI MapID="31" xpos="849.989" ypos="42.9986" zpos="490.252" type="cmm.cmm_marks.cmm_ore.cmm_normore.cmm_copper" GUID="iNndCF7C8kOhGoA1bzDsSg=="/>
		<POI MapID="31" xpos="1044.48" ypos="59.4009" zpos="109.216" type="cmm.cmm_marks.cmm_forage.cmm_herb.cmm_blackpeppercorn" GUID="EfMmxZ3T6UWhrDBeCN3/MQ=="/>
		<POI MapID="31" xpos="1044.44" ypos="59.3726" zpos="106.759" type="cmm.cmm_marks.cmm_forage.cmm_herb.cmm_garlic" GUID="9VlwDoaTRk262M4pzOr0wA=="/>
		<POI MapID="31" xpos="1043.27" ypos="59.289" zpos="108.111" type="cmm.cmm_marks.cmm_forage.cmm_herb.cmm_parsleyleaf" GUID="5wPa1fUPyEWdWrTOtuZbyg=="/>
		<POI MapID="31" xpos="1045.67" ypos="59.3714" zpos="108.041" type="cmm.cmm_marks.cmm_forage.cmm_herb.cmm_thymeleaf" GUID="6ojgkCnKq0WwxK/w8rztsg=="/>
		<POI MapID="31" xpos="920.34" ypos="35.9502" zpos="72.7535" type="cmm.cmm_marks.cmm_forage.cmm_vegetable.cmm_onion" GUID="o8Tg5dkTsUSxDF7Ap3alIA=="/>
		<POI MapID="31" xpos="897.395" ypos="35.7891" zpos="52.0233" type="cmm.cmm_marks.cmm_forage.cmm_vegetable.cmm_carrot" GUID="zKMKbiDZ0kCyEh6N0GDocg=="/>
		<POI MapID="31" xpos="1232.17" ypos="8.62277" zpos="69.3222" type="cmm.cmm_marks.cmm_forage.cmm_fungus.cmm_mushroom" GUID="E3aXVE10uUCu/3A+5Oug7g=="/>
		<POI MapID="31" xpos="1178.49" ypos="27.5453" zpos="13.5445" type="cmm.cmm_marks.cmm_forage.cmm_fungus.cmm_mushroom" GUID="7LpL9c5h30OjL47dyce41g=="/>
		<POI MapID="31" xpos="1173.4" ypos="109.206" zpos="-331.385" type="cmm.cmm_marks.cmm_ore.cmm_normore.cmm_silver" GUID="QyVjH7bo5Uqe7VHIG3Df8Q=="/>
		<POI MapID="31" xpos="939.104" ypos="101.736" zpos="-281.722" type="cmm.cmm_marks.cmm_forage.cmm_herb.cmm_blackpeppercorn" GUID="F4EsmqQhZkaRnZqfGWGI9Q=="/>
		<POI MapID="31" xpos="938.002" ypos="101.732" zpos="-282.855" type="cmm.cmm_marks.cmm_forage.cmm_herb.cmm_parsleyleaf" GUID="NyG7Qsd9R0WQ53jh2zDbfQ=="/>
		<POI MapID="31" xpos="940.136" ypos="101.741" zpos="-282.818" type="cmm.cmm_marks.cmm_forage.cmm_herb.cmm_thymeleaf" GUID="y81VauILIUKxnDOReNgCKA=="/>
		<POI MapID="31" xpos="939.046" ypos="101.731" zpos="-283.96" type="cmm.cmm_marks.cmm_forage.cmm_herb.cmm_garlic" GUID="Zg5hOl8lKEiipjLlA84gJg=="/>
		<POI MapID="31" xpos="863.386" ypos="87.2324" zpos="-310.216" type="cmm.cmm_marks.cmm_ore.cmm_normore.cmm_iron" GUID="f/1yeUc9zEGENjb9YlcSSg=="/>
		<POI MapID="31" xpos="838.947" ypos="68.571" zpos="-247.204" type="cmm.cmm_marks.cmm_forage.cmm_herb.cmm_blackpeppercorn" GUID="R85KVosge02rp5KSHfUS6Q=="/>
		<POI MapID="31" xpos="838.805" ypos="68.583" zpos="-249.359" type="cmm.cmm_marks.cmm_forage.cmm_herb.cmm_garlic" GUID="LIib/JwS0EiRaDryjfaKqA=="/>
		<POI MapID="31" xpos="837.871" ypos="68.5988" zpos="-248.279" type="cmm.cmm_marks.cmm_forage.cmm_herb.cmm_parsleyleaf" GUID="6xuR0qeZ2ECWrehjYaLSjg=="/>
		<POI MapID="31" xpos="839.864" ypos="68.6296" zpos="-248.3" type="cmm.cmm_marks.cmm_forage.cmm_herb.cmm_thymeleaf" GUID="U/Ll8RRVp0mX8/rDtAJPIw=="/>
		<POI MapID="31" xpos="787.599" ypos="73.938" zpos="-319.439" type="cmm.cmm_marks.cmm_ore.cmm_normore.cmm_silver" GUID="4mUZ86pkaUKsqI3FMfypkA=="/>
		<POI MapID="31" xpos="710.651" ypos="48.021" zpos="-233.308" type="cmm.cmm_marks.cmm_ore.cmm_normore.cmm_iron" GUID="YMwcJgVatkSt30YpfEpWcg=="/>
		<POI MapID="31" xpos="564.523" ypos="58.3719" zpos="-88.994" type="cmm.cmm_marks.cmm_ore.cmm_normore.cmm_silver" GUID="GsOyFeAsiUeBNYvqra2ihw=="/>
		<POI MapID="31" xpos="555.654" ypos="51.567" zpos="-66.3026" type="cmm.cmm_marks.cmm_ore.cmm_normore.cmm_silver" GUID="Md9t4g6cWkCF/CfXrLPABg=="/>
		<POI MapID="31" xpos="600.854" ypos="33.7759" zpos="-105.108" type="cmm.cmm_marks.cmm_forage.cmm_fungus.cmm_mushroom" GUID="DOJzyAZ1fUORjpWXHtnFVg=="/>
		<POI MapID="31" xpos="601.888" ypos="35.3835" zpos="-92.1936" type="cmm.cmm_marks.cmm_forage.cmm_fungus.cmm_mushroom" GUID="IEID+cqTQUCgspa1uJsfbQ=="/>
		<POI MapID="31" xpos="712.89" ypos="50.2943" zpos="-69.857" type="cmm.cmm_marks.cmm_ore.cmm_normore.cmm_iron" GUID="cByt5TK+SkqieLylooA/gQ=="/>
		<POI MapID="31" xpos="749.932" ypos="27.7298" zpos="140.415" type="cmm.cmm_marks.cmm_forage.cmm_vegetable.cmm_onion" GUID="BDyoxI5zNkumpAj5MqZdZA=="/>
		<POI MapID="31" xpos="727.698" ypos="33.0397" zpos="182.833" type="cmm.cmm_marks.cmm_wood.cmm_softwood" GUID="luji6V/+sk6qJXrJlDBI4g=="/>
		<POI MapID="31" xpos="587.434" ypos="74.2241" zpos="327.264" type="cmm.cmm_marks.cmm_ore.cmm_normore.cmm_iron" GUID="Mpr7605bVkqJXVULzE3ijA=="/>
		<POI MapID="31" xpos="478.63" ypos="61.5585" zpos="432.591" type="cmm.cmm_marks.cmm_ore.cmm_normore.cmm_iron" GUID="mgBY9T6XXUKw8/iBVANJLQ=="/>
		<POI MapID="31" xpos="405.304" ypos="76.5341" zpos="526.532" type="cmm.cmm_marks.cmm_wood.cmm_softwood" GUID="I9ciiz0Nbki93T4VU3/Osw=="/>
		<POI MapID="31" xpos="309.113" ypos="79.7208" zpos="458.325" type="cmm.cmm_marks.cmm_ore.cmm_normore.cmm_iron" GUID="LjwA0qDYCEuos37JRGSxRw=="/>
		<POI MapID="31" xpos="358.453" ypos="60.9447" zpos="446.144" type="cmm.cmm_marks.cmm_forage.cmm_vegetable.cmm_carrot" GUID="mKj7nr4zjkGXa88/7kFfKQ=="/>
		<POI MapID="31" xpos="339.243" ypos="70.9956" zpos="422.188" type="cmm.cmm_marks.cmm_forage.cmm_vegetable.cmm_carrot" GUID="pzgfl+MbfUSR4yu97C8AvA=="/>
		<POI MapID="31" xpos="383.128" ypos="95.6583" zpos="217.629" type="cmm.cmm_marks.cmm_ore.cmm_normore.cmm_silver" GUID="K366DspTaUumK9X9tJ9wYA=="/>
		<POI MapID="31" xpos="645.606" ypos="32.0036" zpos="159.6" type="cmm.cmm_marks.cmm_wood.cmm_softwood" GUID="Utzq7Vg2jU+m+/Z789h1wA=="/>
		<POI MapID="31" xpos="602.985" ypos="24.9156" zpos="98.9188" type="cmm.cmm_marks.cmm_forage.cmm_vegetable.cmm_onion" GUID="s15hBofCcEiRwzpcSKZRpQ=="/>
		<POI MapID="31" xpos="468.558" ypos="3.74404" zpos="-266.643" type="cmm.cmm_marks.cmm_wood.cmm_softwood" GUID="oRx4gu+DOkmHxnsCWBTGYg=="/>
		<POI MapID="31" xpos="752.584" ypos="112.14" zpos="-439.94" type="cmm.cmm_marks.cmm_forage.cmm_fruit.cmm_strawberry" GUID="vQkkiq6kR0yhUrDCo69UMw=="/>
		<POI MapID="31" xpos="754.353" ypos="112.165" zpos="-436.65" type="cmm.cmm_marks.cmm_forage.cmm_fruit.cmm_strawberry" GUID="E2KYAtBSQ0yu4ii1SAso2A=="/>
		<POI MapID="31" xpos="752.865" ypos="111.568" zpos="-431.37" type="cmm.cmm_marks.cmm_forage.cmm_fruit.cmm_strawberry" GUID="WGzxHZW0BkmD0nk/w1uHCg=="/>
		<POI MapID="31" xpos="758.82" ypos="112.112" zpos="-433.369" type="cmm.cmm_marks.cmm_forage.cmm_fruit.cmm_strawberry" GUID="ebXn9V2L1k2z1FHJwHjb+A=="/>
		<POI MapID="31" xpos="767.35" ypos="112.631" zpos="-435.033" type="cmm.cmm_marks.cmm_forage.cmm_fruit.cmm_strawberry" GUID="kMMyn+wQWk+A9R1W3i06Mg=="/>
		<POI MapID="31" xpos="769.419" ypos="113.532" zpos="-439.01" type="cmm.cmm_marks.cmm_forage.cmm_fruit.cmm_strawberry" GUID="ndg2/3tTX0+jYARMEAn9NA=="/>
		<POI MapID="31" xpos="764.63" ypos="114.628" zpos="-452.542" type="cmm.cmm_marks.cmm_forage.cmm_fruit.cmm_strawberry" GUID="7qFl/P0dHEu6kJMl2PA6wQ=="/>
		<POI MapID="31" xpos="761.319" ypos="114.372" zpos="-451.087" type="cmm.cmm_marks.cmm_forage.cmm_fruit.cmm_strawberry" GUID="g2+0bgVviUC1sI7qSwq/6Q=="/>
		<POI MapID="31" xpos="274.449" ypos="39.8853" zpos="-39.8568" type="cmm.cmm_marks.cmm_ore.cmm_normore.cmm_iron" GUID="e//gcFt9bEOPbsZs3Hrakw=="/>
		<POI MapID="31" xpos="255.255" ypos="40.901" zpos="21.0997" type="cmm.cmm_marks.cmm_wood.cmm_softwood" GUID="AV8Rx1Vc10mE97ecFUQQlg=="/>
		<POI MapID="31" xpos="234.646" ypos="39.7082" zpos="60.4053" type="cmm.cmm_marks.cmm_ore.cmm_normore.cmm_iron" GUID="Hn/mk7sPoka+Yq4IRSRWfg=="/>
		<POI MapID="31" xpos="263.736" ypos="59.4874" zpos="121.85" type="cmm.cmm_marks.cmm_forage.cmm_vegetable.cmm_onion" GUID="UqIC/QGXGkixvF9yTD9JTA=="/>
		<POI MapID="31" xpos="126.354" ypos="84.0836" zpos="191.834" type="cmm.cmm_marks.cmm_forage.cmm_vegetable.cmm_onion" GUID="QWX28JZKKE6SquhN066Z7Q=="/>
		<POI MapID="31" xpos="116.554" ypos="81.0244" zpos="170.205" type="cmm.cmm_marks.cmm_wood.cmm_softwood" GUID="NdPlVqc2DUqxw3gwFqnQeA=="/>
		<POI MapID="31" xpos="95.9058" ypos="68.9324" zpos="128.98" type="cmm.cmm_marks.cmm_forage.cmm_vegetable.cmm_onion" GUID="WRoclVNJsUS7bBaMfTDy1g=="/>
		<POI MapID="31" xpos="124.186" ypos="67.4244" zpos="104.786" type="cmm.cmm_marks.cmm_forage.cmm_vegetable.cmm_carrot" GUID="u7678YEJakGcNaoyjYcaiA=="/>
		<POI MapID="31" xpos="195.97" ypos="111.343" zpos="281.997" type="cmm.cmm_marks.cmm_ore.cmm_normore.cmm_silver" GUID="B/YN7dMF6UeUmXhTt3DERA=="/>
		<POI MapID="31" xpos="134.039" ypos="70.9999" zpos="562.703" type="cmm.cmm_marks.cmm_ore.cmm_normore.cmm_iron" GUID="TGM5hPItuk2ztNteK5cLuw=="/>
		<POI MapID="31" xpos="-341.974" ypos="4.20573" zpos="464.637" type="cmm.cmm_marks.cmm_forage.cmm_vegetable.cmm_carrot" GUID="G4XCUvspvkuBSzzbll37xw=="/>
		<POI MapID="31" xpos="-412.259" ypos="4.09029" zpos="300.496" type="cmm.cmm_marks.cmm_wood.cmm_softwood" GUID="+ywpyqtk7EyLF1RsqQorGA=="/>
		<POI MapID="31" xpos="-644" ypos="53.038" zpos="245.607" type="cmm.cmm_marks.cmm_ore.cmm_normore.cmm_silver" GUID="/OiUIVBhY0Szd2rEG0brpQ=="/>
		<POI MapID="31" xpos="-504.026" ypos="8.2201" zpos="-177.585" type="cmm.cmm_marks.cmm_ore.cmm_normore.cmm_silver" GUID="ZIPQAIXC9kiT1msMHy/Ihg=="/>
		<POI MapID="31" xpos="-455.711" ypos="11.5934" zpos="-211.587" type="cmm.cmm_marks.cmm_wood.cmm_softwood" GUID="pgRTmzX3qE+V1UBRT0iWXQ=="/>
		<POI MapID="31" xpos="-442.511" ypos="15.9088" zpos="-251.21" type="cmm.cmm_marks.cmm_forage.cmm_herb.cmm_blackpeppercorn" GUID="IlT3dOg5jUKTruSmivCq6Q=="/>
		<POI MapID="31" xpos="-442.494" ypos="15.882" zpos="-253.128" type="cmm.cmm_marks.cmm_forage.cmm_herb.cmm_garlic" GUID="iP13swUj1E6g5BOCkR1A3w=="/>
		<POI MapID="31" xpos="-443.495" ypos="15.8895" zpos="-252.12" type="cmm.cmm_marks.cmm_forage.cmm_herb.cmm_parsleyleaf" GUID="Xd0Hb28w0UqO5lZ1qQF76A=="/>
		<POI MapID="31" xpos="-441.404" ypos="15.9003" zpos="-252.244" type="cmm.cmm_marks.cmm_forage.cmm_herb.cmm_thymeleaf" GUID="yshEIuqNYk+stbRKlBuRFA=="/>
		<POI MapID="31" xpos="-296.536" ypos="35.0286" zpos="-215.981" type="cmm.cmm_marks.cmm_ore.cmm_normore.cmm_iron" GUID="aexBFY50AkCsbJ0rmkGNsw=="/>
		<POI MapID="31" xpos="-238.498" ypos="14.3988" zpos="-328.393" type="cmm.cmm_marks.cmm_ore.cmm_normore.cmm_silver" GUID="DVkxTvSFXkWQgyVHdltMuA=="/>
		<POI MapID="31" xpos="-180.195" ypos="14.2825" zpos="-425.976" type="cmm.cmm_marks.cmm_ore.cmm_normore.cmm_silver" GUID="lOWccCMfEE+iaknwYdP3nw=="/>
		<POI MapID="31" xpos="-180.261" ypos="70.9288" zpos="-487.401" type="cmm.cmm_marks.cmm_ore.cmm_normore.cmm_silver" GUID="IdcQE1gfkUOUqgaALuHFag=="/>
		<POI MapID="31" xpos="-260.757" ypos="22.5415" zpos="-466.665" type="cmm.cmm_marks.cmm_ore.cmm_richore.cmm_richiron" GUID="l/YX77vryUympwDLWOPqsg=="/>
		<POI MapID="31" xpos="-114.812" ypos="3.0933" zpos="-339.609" type="cmm.cmm_marks.cmm_ore.cmm_normore.cmm_iron" GUID="JA1pDrHfl0iN1OQv/u8wRA=="/>
		<POI MapID="31" xpos="-226.942" ypos="33.4585" zpos="-82.0566" type="cmm.cmm_marks.cmm_wood.cmm_softwood" GUID="ZkkfsN/bDEaNf5+uTpOWfA=="/>
		<POI MapID="31" xpos="-197.058" ypos="38.3034" zpos="-57.7868" type="cmm.cmm_marks.cmm_forage.cmm_vegetable.cmm_carrot" GUID="jV3KRRZ6i06m9KY5W2dcgQ=="/>
		<POI MapID="31" xpos="-74.7074" ypos="60.9499" zpos="44.9528" type="cmm.cmm_marks.cmm_wood.cmm_softwood" GUID="UxKZk2+g0ES8hTrtOVWuGQ=="/>
		<POI MapID="31" xpos="8.14066" ypos="65.9396" zpos="34.1188" type="cmm.cmm_marks.cmm_wood.cmm_softwood" GUID="+3/0z3VCFU2ANs3exIv9Mg=="/>
		<POI MapID="31" xpos="127.211" ypos="59.0618" zpos="-44.467" type="cmm.cmm_marks.cmm_forage.cmm_herb.cmm_blackpeppercorn" GUID="kZ7LGjsfU0y6PP8nDaPUEQ=="/>
		<POI MapID="31" xpos="127.073" ypos="59.108" zpos="-46.5436" type="cmm.cmm_marks.cmm_forage.cmm_herb.cmm_garlic" GUID="RhMigzlylkS+R/7wQ0fnkQ=="/>
		<POI MapID="31" xpos="126.116" ypos="59.0971" zpos="-45.5339" type="cmm.cmm_marks.cmm_forage.cmm_herb.cmm_parsleyleaf" GUID="8rZNx7uhhUqu1Iq+78oVQw=="/>
		<POI MapID="31" xpos="128.232" ypos="59.1523" zpos="-45.5629" type="cmm.cmm_marks.cmm_forage.cmm_herb.cmm_thymeleaf" GUID="wQ0nokFPHUyzlKRffmCHEA=="/>
		<POI MapID="31" xpos="104.403" ypos="58.4097" zpos="-72.0968" type="cmm.cmm_marks.cmm_forage.cmm_herb.cmm_blackpeppercorn" GUID="gYw2qlyc+k2EnbmGXnqmJQ=="/>
		<POI MapID="31" xpos="104.547" ypos="58.3784" zpos="-74.919" type="cmm.cmm_marks.cmm_forage.cmm_herb.cmm_garlic" GUID="ek2TJL9S0kawIN2nyRkOAw=="/>
		<POI MapID="31" xpos="103.195" ypos="58.3842" zpos="-73.508" type="cmm.cmm_marks.cmm_forage.cmm_herb.cmm_parsleyleaf" GUID="BFiM5O+nGUS1PMek259wSQ=="/>
		<POI MapID="31" xpos="105.94" ypos="58.5507" zpos="-73.5552" type="cmm.cmm_marks.cmm_forage.cmm_herb.cmm_thymeleaf" GUID="GIr3b+AeNkihQHvjz83geQ=="/>
		<POI MapID="31" xpos="212.467" ypos="61.5379" zpos="-27.7531" type="cmm.cmm_marks.cmm_forage.cmm_herb.cmm_blackpeppercorn" GUID="sYlm8L2AGkSlb9FexoVzNA=="/>
		<POI MapID="31" xpos="212.445" ypos="61.4716" zpos="-29.9429" type="cmm.cmm_marks.cmm_forage.cmm_herb.cmm_garlic" GUID="o53ZzM5qmEOEDzHPDnZ0BQ=="/>
		<POI MapID="31" xpos="211.372" ypos="61.4881" zpos="-28.8997" type="cmm.cmm_marks.cmm_forage.cmm_herb.cmm_parsleyleaf" GUID="leXVdFqNjU+RFaSA/xIsXw=="/>
		<POI MapID="31" xpos="213.597" ypos="61.5196" zpos="-28.8719" type="cmm.cmm_marks.cmm_forage.cmm_herb.cmm_thymeleaf" GUID="+p3b2fM3wEuUIyk7re2erg=="/>
		<POI MapID="31" xpos="196.064" ypos="9.79248" zpos="-182.992" type="cmm.cmm_marks.cmm_ore.cmm_normore.cmm_iron" GUID="of/C/sLaeEGrD4brpQpUlg=="/>
		<POI MapID="31" xpos="-463.974" ypos="32.2653" zpos="-510.719" type="cmm.cmm_marks.cmm_ore.cmm_normore.cmm_silver" GUID="rBwSF6jHek2+1Sfb5B8+8w=="/>
		<POI MapID="31" xpos="-552.638" ypos="34.8201" zpos="-546.642" type="cmm.cmm_marks.cmm_ore.cmm_normore.cmm_silver" GUID="wgfGXpkvzEqfEvanJFj87w=="/>
		<POI MapID="31" xpos="-607.783" ypos="39.7033" zpos="-509.308" type="cmm.cmm_marks.cmm_forage.cmm_vegetable.cmm_carrot" GUID="SEI7wLjms0SEvjo1G7+FvQ=="/>
		<POI MapID="31" xpos="-638.057" ypos="50.9858" zpos="-428.316" type="cmm.cmm_marks.cmm_forage.cmm_vegetable.cmm_carrot" GUID="HQJvp5vPbk6VAzyOz/1HWw=="/>
		<POI MapID="31" xpos="-666.938" ypos="31.4513" zpos="-334.253" type="cmm.cmm_marks.cmm_forage.cmm_vegetable.cmm_onion" GUID="GOCraKw+tUOxnc3vrovXQQ=="/>
		<POI MapID="31" xpos="-645.286" ypos="25.81" zpos="-236.957" type="cmm.cmm_marks.cmm_forage.cmm_vegetable.cmm_onion" GUID="LHE8L047QUyoxkf4Ybrgqg=="/>
		<POI MapID="31" xpos="-673.024" ypos="22.9819" zpos="-204.172" type="cmm.cmm_marks.cmm_forage.cmm_vegetable.cmm_onion" GUID="TVKqH5scMUmrbhn47AxBJw=="/>
		<POI MapID="31" xpos="-865.281" ypos="44.583" zpos="37.2683" type="cmm.cmm_marks.cmm_forage.cmm_herb.cmm_blackpeppercorn" GUID="KB928dz8Kka+MHiXxtBiAw=="/>
		<POI MapID="31" xpos="-865.317" ypos="44.5172" zpos="35.2526" type="cmm.cmm_marks.cmm_forage.cmm_herb.cmm_garlic" GUID="e2GLi9vrhkmf9YAl/pjAxg=="/>
		<POI MapID="31" xpos="-866.343" ypos="44.557" zpos="36.2713" type="cmm.cmm_marks.cmm_forage.cmm_herb.cmm_parsleyleaf" GUID="zIJafXIJ60Wi811VMmLAXw=="/>
		<POI MapID="31" xpos="-864.211" ypos="44.5724" zpos="36.2824" type="cmm.cmm_marks.cmm_forage.cmm_herb.cmm_thymeleaf" GUID="7mFozc0x5ECxWC+wicmLRw=="/>
		<POI MapID="31" xpos="-923.025" ypos="65.4152" zpos="215.298" type="cmm.cmm_marks.cmm_ore.cmm_normore.cmm_iron" GUID="SHHWslWnaESLqtG2+wrCCg=="/>
		<POI MapID="31" xpos="-866.02" ypos="71.1409" zpos="272.255" type="cmm.cmm_marks.cmm_wood.cmm_softwood" GUID="OWEUn5qF8UWkS3ySgjIuAw=="/>
		<POI MapID="31" xpos="-749.191" ypos="61.6299" zpos="341.03" type="cmm.cmm_marks.cmm_ore.cmm_normore.cmm_iron" GUID="4rC6EPC0MkarHX78utyXYQ=="/>
		<POI MapID="31" xpos="-726.13" ypos="61.3755" zpos="349.296" type="cmm.cmm_marks.cmm_ore.cmm_normore.cmm_silver" GUID="QoPHFf/7r0iEOYFvvNFLkA=="/>
		<POI MapID="31" xpos="-1062.3" ypos="106.37" zpos="219.243" type="cmm.cmm_marks.cmm_wood.cmm_softwood" GUID="mHoiYQ0WOEGsg+ZPO2xDCA=="/>
		<POI MapID="31" xpos="-996.523" ypos="73.1752" zpos="134.351" type="cmm.cmm_marks.cmm_wood.cmm_softwood" GUID="K43wHRLAYUuPvFjcRUaJCg=="/>
		<POI MapID="31" xpos="-1032.32" ypos="92.3717" zpos="15.059" type="cmm.cmm_marks.cmm_ore.cmm_normore.cmm_iron" GUID="ek3rXIJ/vUySZ8OhHfUymA=="/>
		<POI MapID="31" xpos="-1072.58" ypos="59.4426" zpos="-109.011" type="cmm.cmm_marks.cmm_forage.cmm_herb.cmm_blackpeppercorn" GUID="jgwhcCBv/k+zcXc4XqRuXw=="/>
		<POI MapID="31" xpos="-1072.52" ypos="59.4637" zpos="-110.867" type="cmm.cmm_marks.cmm_forage.cmm_herb.cmm_garlic" GUID="Hwg+UYVyUkOn6CegdAmZkQ=="/>
		<POI MapID="31" xpos="-1073.5" ypos="59.5188" zpos="-109.958" type="cmm.cmm_marks.cmm_forage.cmm_herb.cmm_parsleyleaf" GUID="D/byzVRNvEeR522eYGTBlg=="/>
		<POI MapID="31" xpos="-1071.63" ypos="59.4854" zpos="-109.839" type="cmm.cmm_marks.cmm_forage.cmm_herb.cmm_thymeleaf" GUID="fx/us0CG3EmK8xW7MNWg4A=="/>
		<POI MapID="31" xpos="-1081.6" ypos="59.9649" zpos="-83.1971" type="cmm.cmm_marks.cmm_wood.cmm_softwood" GUID="XPoHNSQo7UKMuEcnfd1Qaw=="/>
		<POI MapID="31" xpos="-1101.43" ypos="67.1787" zpos="-63.0925" type="cmm.cmm_marks.cmm_wood.cmm_softwood" GUID="SePCroBngU68s253JrPO0w=="/>
		<POI MapID="31" xpos="-987.358" ypos="59.9853" zpos="-77.1803" type="cmm.cmm_marks.cmm_wood.cmm_softwood" GUID="jV791K9SI0+/KPVPErrZlQ=="/>
		<POI MapID="31" xpos="-915.919" ypos="54.1242" zpos="-112.36" type="cmm.cmm_marks.cmm_ore.cmm_normore.cmm_iron" GUID="+ErtvdRctUuvWg2yNOS8pg=="/>
		<POI MapID="31" xpos="-1067.04" ypos="46.8745" zpos="-325.223" type="cmm.cmm_marks.cmm_ore.cmm_normore.cmm_iron" GUID="jKUuOghTBE61x53cr4EVvw=="/>
		<POI MapID="31" xpos="-1113.16" ypos="45.6728" zpos="-283.9" type="cmm.cmm_marks.cmm_forage.cmm_vegetable.cmm_carrot" GUID="P4PiHd5ix0WYfdpLDqQx0g=="/>
		<POI MapID="31" xpos="-1158.91" ypos="52.5335" zpos="-424.982" type="cmm.cmm_marks.cmm_forage.cmm_fungus.cmm_mushroom" GUID="fPZSFl73C0eriPcjPOcn+Q=="/>
		<POI MapID="31" xpos="-886.656" ypos="52.2584" zpos="-467.771" type="cmm.cmm_marks.cmm_forage.cmm_fungus.cmm_mushroom" GUID="41QPTBgOIkmrCKUe15mzHQ=="/>
		<POI MapID="31" xpos="-839.607" ypos="55.5986" zpos="-482.949" type="cmm.cmm_marks.cmm_ore.cmm_normore.cmm_silver" GUID="aUkOQNUXQ02e+ss7KfmgbA=="/>
		<POI MapID="31" xpos="-814.378" ypos="53.9983" zpos="-584.097" type="cmm.cmm_marks.cmm_ore.cmm_normore.cmm_iron" GUID="LdMlCduWUEuNbFNY4ls6bw=="/>
		<POI MapID="31" xpos="-757.519" ypos="58.5712" zpos="-515.731" type="cmm.cmm_marks.cmm_ore.cmm_normore.cmm_iron" GUID="chALJUx3MEqDFatLIcLFRg=="/>
	</POIs>
</OverlayData>
