<OverlayData>
	<POIs>
		<POI MapID="1015" xpos="407.558" ypos="414.006" zpos="-385.309" type="cmm.cmm_marks.cmm_wood.cmm_elderwood" GUID="NJMJ1yOJw0OR4ilIQJOJdQ=="/>
		<POI MapID="1015" xpos="278.711" ypos="413.341" zpos="-405.179" type="cmm.cmm_marks.cmm_ore.cmm_normore.cmm_mithril" GUID="spUjNJIql0SLSv3SOJF1hQ=="/>
		<POI MapID="1015" xpos="87.8233" ypos="414.85" zpos="-415.748" type="cmm.cmm_marks.cmm_wood.cmm_elderwood" GUID="aF1EvQR10USaJQ5grxhnOA=="/>
		<POI MapID="1015" xpos="142.737" ypos="413.986" zpos="-293.445" type="cmm.cmm_marks.cmm_ore.cmm_normore.cmm_mithril" GUID="T/DWb2HdEEahkqGhJy30Pw=="/>
		<POI MapID="1015" xpos="191.78" ypos="414.072" zpos="-209.058" type="cmm.cmm_marks.cmm_ore.cmm_richore.cmm_richmithril" GUID="sZYYlQYQ/EipFzwltR3euw=="/>
		<POI MapID="1015" xpos="185.632" ypos="414.728" zpos="-237.372" type="cmm.cmm_marks.cmm_wood.cmm_elderwood" GUID="XwR/Wcb74kerHJbvjQFCYw=="/>
		<POI MapID="1015" xpos="102.941" ypos="449.685" zpos="-211.454" type="cmm.cmm_marks.cmm_wood.cmm_ancientwood" GUID="K/Y4wz/MRkC5lV5bE5KEAQ=="/>
		<POI MapID="1015" xpos="28.8249" ypos="413.098" zpos="-269.976" type="cmm.cmm_marks.cmm_ore.cmm_normore.cmm_mithril" GUID="+AjNEMz2k0Oced2ru1o7/Q=="/>
		<POI MapID="1015" xpos="-60.5376" ypos="415.805" zpos="-263.199" type="cmm.cmm_marks.cmm_wood.cmm_elderwood" GUID="6YFEIpIR80Gr+jU0w8tvsw=="/>
		<POI MapID="1015" xpos="-115.343" ypos="416.917" zpos="-276.409" type="cmm.cmm_marks.cmm_ore.cmm_normore.cmm_mithril" GUID="mqWJmdKezEuwBLoX0333UQ=="/>
		<POI MapID="1015" xpos="-120.472" ypos="414.952" zpos="-348.648" type="cmm.cmm_marks.cmm_wood.cmm_ancientwood" GUID="hVkaMoVq/keWlGjKLmr7Ig=="/>
		<POI MapID="1015" xpos="-95.5168" ypos="416.837" zpos="-201.128" type="cmm.cmm_marks.cmm_wood.cmm_elderwood" GUID="E2wu3mQhWEqTqLW8TaC1fw=="/>
		<POI MapID="1015" xpos="-270.424" ypos="420.358" zpos="-112.202" type="cmm.cmm_marks.cmm_ore.cmm_normore.cmm_mithril" GUID="rCWVSG8dukiPBCbVVNIqCg=="/>
		<POI MapID="1015" xpos="-263.993" ypos="421.051" zpos="-95.7579" type="cmm.cmm_marks.cmm_wood.cmm_elderwood" GUID="iVIcTqO/40SS9quB7XxD0A=="/>
		<POI MapID="1015" xpos="-318.806" ypos="432.595" zpos="-62.8675" type="cmm.cmm_marks.cmm_ore.cmm_richore.cmm_richmithril" GUID="1VNqZgOJFUiqUQs78hxtCA=="/>
		<POI MapID="1015" xpos="-309.633" ypos="429.139" zpos="-46.2688" type="cmm.cmm_marks.cmm_ore.cmm_normore.cmm_mithril" GUID="RqTXJXoaiE2wYRCyIroi5g=="/>
		<POI MapID="1015" xpos="-224.98" ypos="418.215" zpos="31.4652" type="cmm.cmm_marks.cmm_wood.cmm_elderwood" GUID="rtRx1M9wgk2qu0Akqzmc2Q=="/>
		<POI MapID="1015" xpos="-326.823" ypos="439.633" zpos="36.541" type="cmm.cmm_marks.cmm_ore.cmm_normore.cmm_mithril" GUID="LZ7NsOWlW0OSKfBXUwakPg=="/>
		<POI MapID="1015" xpos="-120.397" ypos="417.44" zpos="40.5628" type="cmm.cmm_marks.cmm_wood.cmm_elderwood" GUID="6d5OaC2onEep8NsAX6RqcQ=="/>
		<POI MapID="1015" xpos="-93.085" ypos="413.848" zpos="131.675" type="cmm.cmm_marks.cmm_wood.cmm_elderwood" GUID="GE8U/EsYm0imiOghVufiuA=="/>
		<POI MapID="1015" xpos="-53.3309" ypos="417.695" zpos="243.549" type="cmm.cmm_marks.cmm_ore.cmm_normore.cmm_mithril" GUID="cthyVnvckEmu12b5hkKMrw=="/>
		<POI MapID="1015" xpos="-12.0435" ypos="404.735" zpos="187.706" type="cmm.cmm_marks.cmm_wood.cmm_elderwood" GUID="rAr+14xr5UyOnVfU7AI7dA=="/>
		<POI MapID="1015" xpos="198.257" ypos="415.418" zpos="-84.7728" type="cmm.cmm_marks.cmm_wood.cmm_elderwood" GUID="hmALkth24UWA1xIS+n479g=="/>
		<POI MapID="1015" xpos="460.023" ypos="389.972" zpos="-14.14" type="cmm.cmm_marks.cmm_ore.cmm_normore.cmm_orichalcum" GUID="uSbOgdEPZE29mRmgQBKm/g=="/>
		<POI MapID="1015" xpos="99.9637" ypos="401.131" zpos="268.489" type="cmm.cmm_marks.cmm_wood.cmm_elderwood" GUID="Z3hrJz19eUyrUNkqIghxFg=="/>
		<POI MapID="1015" xpos="156.016" ypos="397.385" zpos="363.554" type="cmm.cmm_marks.cmm_wood.cmm_elderwood" GUID="LIQqNVL7J0u4CjpRznar5Q=="/>
	</POIs>
</OverlayData>
